CHANGELOG.md
CONTRIBUTING.md
README.md
broadworks_ocip/__init__.py
broadworks_ocip/api.py
broadworks_ocip/base.py
broadworks_ocip/exceptions.py
broadworks_ocip/requests.py
broadworks_ocip/responses.py
broadworks_ocip/types.py
docs/changelog.md
docs/contributing.md
docs/index.md
docs/internals.md
docs/license.md
docs/todo.md
docs/usage.md
tests/__init__.py
tests/fakeserver.py
tests/test_basic_command_xml.py
tests/test_fake_server.py
tests/test_faulty_command.py
tests/test_xml_command_decode.py
tests/test_xml_session_id.py
broadworks_ocip-2.2.0.dist-info/METADATA
broadworks_ocip-2.2.0.dist-info/WHEEL
broadworks_ocip-2.2.0.dist-info/LICENSE
broadworks_ocip-2.2.0.dist-info/RECORD
