Metadata-Version: 2.1
Name: broadworks-ocip
Version: 2.2.0
Summary: API interface to the OCI-P provisioning interface of a Broadworks softswitch
Home-page: https://pypi.org/project/broadworks-ocip/
License: BSD
Author: Nigel Metheringham
Author-email: nigelm@cpan.org
Requires-Python: >=3.6.2
Classifier: Development Status :: 2 - Pre-Alpha
Classifier: Intended Audience :: Developers
Classifier: License :: OSI Approved :: BSD License
Classifier: License :: Other/Proprietary License
Classifier: Natural Language :: English
Classifier: Programming Language :: Python :: 3
Classifier: Programming Language :: Python :: 3.7
Classifier: Programming Language :: Python :: 3.8
Classifier: Programming Language :: Python :: 3.9
Classifier: Programming Language :: Python :: 3.10
Classifier: Programming Language :: Python :: 3.11
Classifier: Programming Language :: Python :: 3
Classifier: Programming Language :: Python :: 3.10
Classifier: Programming Language :: Python :: 3.6
Classifier: Programming Language :: Python :: 3.7
Classifier: Programming Language :: Python :: 3.8
Classifier: Programming Language :: Python :: 3.9
Classifier: Topic :: Software Development :: Libraries :: Python Modules
Requires-Dist: attrs (>=21.4.0,<22.0.0)
Requires-Dist: lxml (==4.9.4)
Requires-Dist: null-object (>=0.1.0,<0.2.0)
Requires-Dist: pyyaml (==6.0.1)
Project-URL: Documentation, https://nigelm.github.io/broadworks_ocip/
Project-URL: Repository, https://github.com/nigelm/broadworks_ocip
